<?xml version="1.0" encoding="utf-8" ?><dwsync><file name="blog_entry.php" server="91.208.99.4" local="3486449268" remote="323953104393148244" Dst="-1" /><file name="default.php" server="91.208.99.4" local="3486449268" remote="323953104402180104" Dst="-1" /><file name="description.txt" server="91.208.99.4" local="3486449268" remote="323953104393148244" Dst="-1" /><file name="full.php" server="91.208.99.4" local="3486449268" remote="323953104401150624" Dst="-1" /><file name="home.php" server="91.208.99.4" local="3486449268" remote="323953104393148244" Dst="-1" /><file name="index.html" server="91.208.99.4" local="3486449269" remote="323953104393148244" Dst="-1" /><file name="left_sidebar.php" server="91.208.99.4" local="3486449270" remote="323953104393148244" Dst="-1" /><file name="main.css" server="91.208.99.4" local="3486529722" remote="323953104402786944" Dst="-1" /><file name="members.css" server="91.208.99.4" local="3486449270" remote="323953104392603624" Dst="-1" /><file name="members.php" server="91.208.99.4" local="3486449270" remote="323953104393148244" Dst="-1" /><file name="product_detail.php" server="91.208.99.4" local="3486449270" remote="323953104402179864" Dst="-1" /><file name="resources_home.php" server="91.208.99.4" local="3486449270" remote="323953104401089424" Dst="-1" /><file name="thumbnail.png" server="91.208.99.4" local="3486449270" remote="323953104393148244" Dst="-1" /><file name="tooltip.html" server="91.208.99.4" local="3486449270" remote="323953104393148244" Dst="-1" /><file name="typography.css" server="91.208.99.4" local="3486449270" remote="323953104393148244" Dst="-1" /><file name="view.php" server="91.208.99.4" local="3486449270" remote="323953104401081324" Dst="-1" /></dwsync>